setup.py
bin/brewery
bin/mongoaudit
brewery/__init__.py
brewery/common.py
brewery/flow.py
brewery/metadata.py
brewery/probes.py
brewery/streams.py
brewery/utils.py
brewery.egg-info/PKG-INFO
brewery.egg-info/SOURCES.txt
brewery.egg-info/dependency_links.txt
brewery.egg-info/top_level.txt
brewery/dq/__init__.py
brewery/dq/base.py
brewery/dq/field_statistics.py
brewery/ds/__init__.py
brewery/ds/base.py
brewery/ds/csv_streams.py
brewery/ds/gdocs_streams.py
brewery/ds/html_target.py
brewery/ds/mongo_streams.py
brewery/ds/sql_streams.py
brewery/ds/stream_auditor.py
brewery/ds/xls_streams.py
brewery/ds/yaml_dir_streams.py
brewery/nodes/__init__.py
brewery/nodes/base.py
brewery/nodes/field_nodes.py
brewery/nodes/record_nodes.py
brewery/nodes/source_nodes.py
brewery/nodes/target_nodes.py
brewery/opendata/__init__.py
brewery/opendata/scraperwiki.py
brewery/server/__init__.py
brewery/tests/__init__.py
brewery/tests/test_data_quality.py
brewery/tests/test_data_source.py
brewery/tests/test_field_list.py
brewery/tests/test_forks.py
brewery/tests/test_node_stream.py
brewery/tests/test_nodes.py
brewery/tests/test_pipes.py
brewery/tests/test_sql_streams.py
brewery/tests/test_suite.py
tests/__init__.py
tests/test_data_quality.py
tests/test_data_source.py
tests/test_field_list.py
tests/test_forks.py
tests/test_node_stream.py
tests/test_nodes.py
tests/test_pipes.py
tests/test_sql_streams.py
tests/test_suite.py