Metadata-Version: 1.0
Name: brewery
Version: 0.8.0
Summary: Framework for analysing data and measuring quality of data using structured data streams
Home-page: http://www.databrewery.org
Author: Stefan Urbanek
Author-email: stefan.urbanek@gmail.com
License: MIT
Keywords: data analysis quality datamining
Platform: UNKNOWN
Classifier: Development Status :: 4 - Beta
Classifier: Intended Audience :: Developers
Classifier: Intended Audience :: Science/Research
Classifier: License :: OSI Approved :: MIT License
Classifier: Programming Language :: Python
Classifier: Topic :: Database
Classifier: Topic :: Scientific/Engineering
Classifier: Topic :: Utilities
